flairjsonnlp/__init__.py
flairjsonnlp/server.py
tests/__init__.py
tests/mocks.py
tests/test_flairjsonnlp.py
flairjsonnlp-0.0.9.dist-info/LICENSE
flairjsonnlp-0.0.9.dist-info/METADATA
flairjsonnlp-0.0.9.dist-info/WHEEL
flairjsonnlp-0.0.9.dist-info/top_level.txt
flairjsonnlp-0.0.9.dist-info/RECORD
