Metadata-Version: 2.1
Name: flairjsonnlp
Version: 0.0.9
Summary: The Python Flair JSON-NLP package
Home-page: https://github.com/dcavar/Flair-JSON-NLP
Author: Damir Cavar, Oren Baldinger, Maanvitha Gongalla, Anurag Kumar, Murali Kammili, Boli Fang
Author-email: damir@semiring.com
License: UNKNOWN
Platform: UNKNOWN
Classifier: Programming Language :: Python :: 3
Classifier: License :: OSI Approved :: Apache Software License
Classifier: Operating System :: OS Independent
Requires-Dist: flair (>=0.4.1)
Requires-Dist: pyjsonnlp (>=0.2.6)
